pytt/__init__.py
pytt/config.py
pytt/db.py
pytt/main.py
pytt/plotting.py
pytt/table.py
pytt/utils.py
pytt-0.1.0.dist-info/entry_points.txt
pytt-0.1.0.dist-info/WHEEL
pytt-0.1.0.dist-info/METADATA
pytt-0.1.0.dist-info/RECORD
