Metadata-Version: 2.1
Name: pytt
Version: 0.1.0
Summary: Python Time Tracker
Home-page: https://github.com/pajecawav/pytt
Author: pajecawav
Author-email: pajecawav@gmail.com
Requires-Python: >=3.6,<4.0
Classifier: Programming Language :: Python :: 3
Classifier: Programming Language :: Python :: 3.6
Classifier: Programming Language :: Python :: 3.7
Classifier: Programming Language :: Python :: 3.8
Classifier: Programming Language :: Python :: 3.9
Requires-Dist: typer (>=0.3.2,<0.4.0)
Project-URL: Repository, https://github.com/pajecawav/pytt
